{"type": "playbook", "spec_version": "1.0", "id": "playbook--6b74199d-42a6-43a1-99cb-75d52207a778", "name": "Prevent FuzzyPanda Malware", "description": "This playbook will block traffic to the FuzzyPanda data exfil site", "playbook_types": ["prevention"], "created_by": "identity--uuid2", "created": "2021-04-19T23:32:24.399Z", "modified": "2021-04-19T23:32:24.399Z", "valid_from": "2021-04-19T23:32:24.39964Z", "valid_until": "2021-12-31T23:59:59.999999Z", "derived_from": ["playbook--uuid50"], "priority": 3, "severity": 70, "impact": 5, "labels": "apt", "external_references": [{"name": "ACME Security FuzzyPanda Report  security-playbooks-v1.0 cs02 23 June 2021 Standards Track Work Product Copyright OASIS Open 2021. All Rights Reserved. Page 75 of 100", "description": "ACME security review of FuzzyPanda 2021", "source": "ACME Security Company, Solutions for FuzzyPanda 2021, January 2021. Available online: http://www.example.com/info/fuzzypanda2021.html", "url": "http://www.example.com/info/fuzzypanda2020.html", "external_id": "fuzzypanda 2021.01", "reference_id": "malware--2008c526-508f-4ad4-a565-b84a4949b2af"}], "features": {"parallel_processing": true, "data_markings": true}, "markings": "marking-tlp--a099a2eb-1113-4368-9b17-d7ef75841239", "workflow_start": "start--7269bda2-e651-44d3-9fe5-aa7e88484b93", "workflow": {"type": "start", "on_completion": "single--a13c8450-2bd1-4a2b-9241-cf4f7e9f48cb", "name": "Receive IOC", "description": "Get FuzzyPanda Data Exfil Site IP Address of 1.2.3.4", "commands": [{"type": "manual", "command": "Open SIEM solution and add rule to look for 1.2.3.4"}], "next_steps": "single--3d930f08-e22c-4dd4-996f-61f2d022121c"}, "data_marking_definitions": {"marking-statement--16a48f6b-ab42-4f99-ba9b-8b21e1225836": {"type": "marking-statement", "spec_version": "1.0", "id": "marking-statement--16a48f6b-ab42-4f99-ba9b-8b21e1225836", "created": "2021-04-19T23:32:24.399Z", "modified": "2021-04-19T23:32:24.399Z, security-playbooks-v1.0-cs02 23 June 2021 Standards Track Work Product Copyright \u00a9 OASIS Open 2021. All Rights Reserved. Page 77 of 100", "statement": "Copyright 2021 ACME Security Company"}, "marking-tlp--a099a2eb-1113-4368-9b17-d7ef75841239": {"type": "marking-tlp", "spec_version": "1.0", "id": "marking-tlp--a099a2eb-1113-4368-9b17-d7ef75841239", "created": "2021-04-19T23:32:24.399Z", "modified": "2021-04-19T23:32:24.399Z", "tlp_level": "TLP-GREEN"}}}